MANIFEST.in
Makefile
README.rst
setup.py
tgrocery/__init__.py
tgrocery/base.py
tgrocery/classifier.py
tgrocery/converter.py
tgrocery.egg-info/PKG-INFO
tgrocery.egg-info/SOURCES.txt
tgrocery.egg-info/dependency_links.txt
tgrocery.egg-info/requires.txt
tgrocery.egg-info/top_level.txt
tgrocery/learner/Makefile
tgrocery/learner/__init__.py
tgrocery/learner/learner.py
tgrocery/learner/test.cpp
tgrocery/learner/util.c
tgrocery/learner/liblinear/Makefile
tgrocery/learner/liblinear/linear.cpp
tgrocery/learner/liblinear/linear.h
tgrocery/learner/liblinear/predict.c
tgrocery/learner/liblinear/train.c
tgrocery/learner/liblinear/tron.cpp
tgrocery/learner/liblinear/tron.h
tgrocery/learner/liblinear/blas/Makefile
tgrocery/learner/liblinear/blas/blas.h
tgrocery/learner/liblinear/blas/blasp.h
tgrocery/learner/liblinear/blas/daxpy.c
tgrocery/learner/liblinear/blas/ddot.c
tgrocery/learner/liblinear/blas/dnrm2.c
tgrocery/learner/liblinear/blas/dscal.c
tgrocery/learner/liblinear/python/Makefile
tgrocery/learner/liblinear/python/liblinear.py
tgrocery/learner/liblinear/python/liblinearutil.py