Metadata-Version: 1.0
Name: tgrocery
Version: 0.1.4
Summary: A simple short-text classification tool based on LibLinear
Home-page: https://github.com/2shou/TextGrocery
Author: 2shou
Author-email: gavin.zgz@gmail.com
License: BSD
Keywords: text classification svm liblinear libshorttext
Platform: UNKNOWN
